SeisSrcInv/__init__.py
SeisSrcInv/inversion.py
SeisSrcInv/plot.py
SeisSrcInv/prep_inv_input_data.py
SeisSrcInv/remove_sws.py
SeisSrcInv-0.0.8.dist-info/LICENSE
SeisSrcInv-0.0.8.dist-info/METADATA
SeisSrcInv-0.0.8.dist-info/WHEEL
SeisSrcInv-0.0.8.dist-info/top_level.txt
SeisSrcInv-0.0.8.dist-info/RECORD
