Metadata-Version: 2.1
Name: SeisSrcInv
Version: 0.0.8
Summary: A full waveform seismic source mechanism inversion package
Home-page: https://github.com/TomSHudson/SeisSrcInv
Author: Tom Hudson
Author-email: tsh37@alumni.cam.ac.uk
License: UNKNOWN
Platform: UNKNOWN
Classifier: Development Status :: 4 - Beta
Classifier: Programming Language :: Python :: 3
Classifier: License :: OSI Approved :: MIT License
Classifier: Operating System :: OS Independent
